pytimicer_c/__init__.py
pytimicer_c/pytimicer_c.py
pytimicer_c-0.13.dist-info/METADATA
pytimicer_c-0.13.dist-info/WHEEL
pytimicer_c-0.13.dist-info/top_level.txt
pytimicer_c-0.13.dist-info/RECORD
