Metadata-Version: 2.1
Name: pytimicer_c
Version: 0.13
Requires-Dist: requests
Requires-Dist: pywin32 ; sys_platform == "win32"
